ifmO3r/__init__.py
ifmO3r/ifm3dTiny/__init__.py
ifmO3r/ifm3dTiny/device.py
ifmO3r/ifm3dTiny/grabber.py
ifmO3r/ifm3dTiny/logger.py
ifmO3r/ifm3dTiny/utils/Receiver.py
ifmO3r/ifm3dTiny/utils/__init__.py
ifmO3r/ifm3dTiny/utils/encoding.py
ifmO3r/ifm3dTiny/utils/hdf5dict.py
ifmO3r/ifm3dTiny/utils/hdf5syntron.py
ifmO3r/ifm3dTiny/utils/ifm3dTinyExceptions.py
ifmO3r/ifm3dTiny/utils/ifmhdf5_format.py
ifmO3r/ifm3dTiny/utils/pcicV3.py
ifmO3r/ifm3dTiny/utils/plotHelper.py
ifmO3r/ifm3dTiny/utils/reboot.py
ifmO3r/ifm3dTiny/utils/recorder.py
ifmO3r/ifm3dTiny/utils/server.py
ifmO3r/ifm3dTiny/utils/sockets.py
ifmO3r/ifm3dTiny/utils/statusLogger.py
ifmO3r/ifm3dTiny/utils/utils.py
ifmO3r/o3ralgo/__init__.py
ifmO3r/o3ralgo/o3r_uncompress_di.py
ifmO3r/pcic/__init__.py
ifmO3r/pcic/client.py
ifmO3r/pcic/cwrappers.py
ifmO3r/pcic/formatClient.py
ifmO3r/pcic/imageClient.py
ifmO3r/pcic/imageClient2D.py
ifmO3r/rpc/__init__.py
ifmO3r/rpc/application.py
ifmO3r/rpc/client.py
ifmO3r/rpc/edit.py
ifmO3r/rpc/session.py
ifmO3r-0.1.3.dist-info/LICENSE
ifmO3r-0.1.3.dist-info/LICENSE.MIT
ifmO3r-0.1.3.dist-info/METADATA
ifmO3r-0.1.3.dist-info/WHEEL
ifmO3r-0.1.3.dist-info/top_level.txt
ifmO3r-0.1.3.dist-info/RECORD
