Metadata-Version: 2.1
Name: ifmO3r
Version: 0.1.3
Summary: ifm o3r library
Home-page: https://www.ifm3d.com
Author-email: sebastian.voegele@ifm.com
License: Apache 2.0 License
Keywords: ifm,o3r,3d
Platform: UNKNOWN
Classifier: License :: OSI Approved :: Apache Software License
Classifier: Programming Language :: Python :: 3
Requires-Dist: h5py (<=3.1.0)
Requires-Dist: matplotlib (>=3.3.3)
Requires-Dist: numpy (>=1.17.5)
